license
disquest_utils/__init__.py
disquest_utils/levels.py
disquest_utils/users.py
disquest_utils-1.1.0.dist-info/LICENSE
disquest_utils-1.1.0.dist-info/WHEEL
disquest_utils-1.1.0.dist-info/METADATA
disquest_utils-1.1.0.dist-info/RECORD
