Metadata-Version: 2.1
Name: disquest-utils
Version: 1.1.0
Summary: A set of async utils for Miku's DisQuest Cog
Home-page: https://github.com/No767/DisQuest-Utils
License: Apache-2.0
Author: No767
Author-email: 73260931+No767@users.noreply.github.com
Requires-Python: >=3.7,<4.0
Classifier: Development Status :: 5 - Production/Stable
Classifier: Framework :: AsyncIO
Classifier: Intended Audience :: Developers
Classifier: License :: OSI Approved :: Apache Software License
Classifier: Operating System :: OS Independent
Classifier: Programming Language :: Python :: 3
Classifier: Programming Language :: Python :: 3.10
Classifier: Programming Language :: Python :: 3.7
Classifier: Programming Language :: Python :: 3.8
Classifier: Programming Language :: Python :: 3.9
Classifier: Programming Language :: Python :: Implementation :: CPython
Provides-Extra: asyncmy
Requires-Dist: SQLAlchemy (>=1.4.40,<2.0.0)
Requires-Dist: asyncmy (>=0.2.5,<0.3.0); extra == "asyncmy"
Requires-Dist: asyncpg (>=0.26.0,<0.27.0)
Requires-Dist: uvloop (>=0.16.0,<0.17.0)
Project-URL: Repository, https://github.com/No767/DisQuest-Utils
